{
	"format_version": "1.13.0",
	"minecraft:feature_rules": {
		"description": {
			"identifier": "minecraft:overworld_blaststone_caves_extra_dirt",
			"places_feature": "yanasakana:underground_dirt_patch"
		},
		"conditions": {
			"placement_pass": "underground_pass",
			"minecraft:biome_filter": [
				{
					"any_of": [
						{
							"test": "has_biome_tag",
							"operator": "==",
							"value": "taiga"
						},
						{
							"test": "has_biome_tag",
							"operator": "==",
							"value": "taiga_hills"
						},
						{
							"test": "has_biome_tag",
							"operator": "==",
							"value": "taiga_mutated"
						}
					]
				}
			]
		},
		"distribution": {
			"iterations": 10,
			"scatter_chance": 100,
			"coordinate_eval_order": "zyx",
			"x": {
				"distribution": "uniform",
				"extent": [
					0,
					16
				]
			},
			"y": {
				"distribution": "uniform",
				"extent": [
					5,
					30
				]
			},
			"z": {
				"distribution": "uniform",
				"extent": [
					0,
					16
				]
			}
		}
	}
}